{
  "link": "https://z-bau.com/programm/2022-12-03/galerie-saal/stage-for-peace-festival",
  "event": "Stage For Peace Festival",
  "text": "> Stage for Peace ist ein soziales Projekt, das im Winter 2015 mit der Intention gegründet wurde Konzerte zu organisieren, deren gesamter Gewinn Initiativen für Menschen auf der Flucht zu Gute kommt.<br />Seit 2016 veranstalten wir Konzerte und Festivals, deren gesamter Gewinn an Geflüchteteninitaitven gespendet wird. So konnten schon über 10.000 € gespendet werden. Unser aktives Engagement der letzten Jahre wurde dieses Jahr mit dem 1. Preis des „Mosaik Jugendpreises – Mit Vielfalt gegen Rassismus“ ausgezeichnet. Einer Würdigung der Städte Nürnberg und München für antirassistische und interkulturelle dialogfördernde Projekte.Dabei helfen alle zusammen: SfP organisiert das Event ehrenamtlich, die Location wird umsonst gestellt und die Acts verzichten auf ihre Gage. Da wir wollen, dass alle Zugang zu unseren Kulturangeboten haben, ist der Eintritt immer auf Spendenbasis – es wird gegeben was der Geldbeutel zulässt. Unser Motto: “ love music, hate hate! ”.Der Gewinn wird vollständig an die NGO Collective Aid ( https://www.collectiveaidngo.org/ ) gehen und ihre Projekte in Serbien unterstützen.Wir wollen einen Raum schaffen, um Konzerte zu genießen und gleichzeitig über die aktuelle Lage für Geflüchtete aufzuklären. Der Fokus wird dabei auf den Pushbacks und den systematischen Menschenrechtsverletzungen an den EU-Außengrenzen . Hierfür soll mit lokalen Initiativen sowie vor Ort arbeitenden NGOs zusammengearbeitet werden. </",
  "date": "2022-12-03",
  "location": "galerie-saal"
}
